LICENSE
MANIFEST.in
README.md
README.rst
requirements.txt
setup.py
metabolabpytools/__init__.py
metabolabpytools/analysis.py
metabolabpytools/isotopomerAnalysis.py
metabolabpytools/isotopomerAnalysis1.py
metabolabpytools.egg-info/PKG-INFO
metabolabpytools.egg-info/SOURCES.txt
metabolabpytools.egg-info/dependency_links.txt
metabolabpytools.egg-info/requires.txt
metabolabpytools.egg-info/top_level.txt
metabolabpytools/jupyter/.DS_Store
metabolabpytools/jupyter/gcmsData1.xlsx
metabolabpytools/jupyter/hsqcData1.xlsx
metabolabpytools/jupyter/isotopomer_analysis_nn_training.ipynb
metabolabpytools/jupyter/isotopomeranalysis_nn.ipynb
metabolabpytools/jupyter/nn_isotopmer_distribution.ipynb
metabolabpytools/jupyter/read_isotopomer_data.ipynb
metabolabpytools/jupyter/read_isotopomer_data_nn.ipynb
metabolabpytools/jupyter/sim_isotopomer_distribution.ipynb
metabolabpytools/jupyter/test.py