Metadata-Version: 2.2
Name: metabolabpytools
Version: 0.9.67
Summary: Tools for metabolomics and metabolism tracing data
Home-page: https://github.com/ludwigc/metabolabpytools
Author: Christian Ludwig
Author-email: C.Ludwig@bham.ac.uk 
License: GPLv3
Keywords: Metabolomics,Tracing,NMR,Data Processing,13C
Platform: MacOS, Windows, UNIX
Classifier: Programming Language :: Python :: 3
Classifier: Programming Language :: Python :: 3.9
Classifier: Topic :: Scientific/Engineering :: Bio-Informatics
Classifier: Topic :: Scientific/Engineering :: Chemistry
Classifier: Topic :: Utilities
Classifier: License :: OSI Approved :: GNU General Public License v3 (GPLv3)
Classifier: Operating System :: OS Independent
License-File: LICENSE
Requires-Dist: numpy
Requires-Dist: scipy
Requires-Dist: pandas
Dynamic: author
Dynamic: author-email
Dynamic: classifier
Dynamic: description
Dynamic: home-page
Dynamic: keywords
Dynamic: license
Dynamic: platform
Dynamic: requires-dist
Dynamic: summary
